{
  "albums": {
    "href": "https://api.spotify.com/v1/search?query=radiohead&type=album&market=US&offset=0&limit=20",
    "items": [
      {
        "album_type": "album",
        "artists": [
          {
            "external_urls": {
              "spotify": "https://open.spotify.com/artist/4Z8W4fKeB5YxbusRsdQVPb"
            },
            "href": "https://api.spotify.com/v1/artists/4Z8W4fKeB5YxbusRsdQVPb",
            "id": "4Z8W4fKeB5YxbusRsdQVPb",
            "name": "Radiohead",
            "type": "artist",
            "uri": "spotify:artist:4Z8W4fKeB5YxbusRsdQVPb"
          }
        ],
        "available_markets": [
          "AD",
          "AR",
          "AT",
          "AU",
          "BE",
          "BG",
          "BO",
          "BR",
          "CA",
          "CH",
          "CL",
          "CO",
          "CR",
          "CY",
          "CZ",
          "DE",
          "DK",
          "DO",
          "EC",
          "EE",
          "ES",
          "FI",
          "FR",
          "GB",
          "GR",
          "GT",
          "HK",
          "HN",
          "HU",
          "ID",
          "IE",
          "IL",
          "IS",
          "IT",
          "JP",
          "LI",
          "LT",
          "LU",
          "LV",
          "MC",
          "MT",
          "MX",
          "MY",
          "NI",
          "NL",
          "NO",
          "NZ",
          "PA",
          "PE",
          "PH",
          "PL",
          "PT",
          "PY",
          "RO",
          "SE",
          "SG",
          "SK",
          "SV",
          "TH",
          "TR",
          "TW",
          "US",
          "UY",
          "VN",
          "ZA"
        ],
        "external_urls": {
          "spotify": "https://open.spotify.com/album/7dxKtc08dYeRVHt3p9CZJn"
        },
        "href": "https://api.spotify.com/v1/albums/7dxKtc08dYeRVHt3p9CZJn",
        "id": "7dxKtc08dYeRVHt3p9CZJn",
        "images": [
          {
            "height": 640,
            "url": "https://i.scdn.co/image/f89c1ecdd0cc5a23d5ad7303d4ae231d197dde98",
            "width": 640
          },
          {
            "height": 300,
            "url": "https://i.scdn.co/image/1b898f0b8e3ce499d0fc629a1918c144d982e475",
            "width": 300
          },
          {
            "height": 64,
            "url": "https://i.scdn.co/image/faf295a70a6531826a8c25d33aad7d2cd9c75c7a",
            "width": 64
          }
        ],
        "name": "OK Computer",
        "release_date": "1997-05-28",
        "release_date_precision": "day",
        "type": "album",
        "uri": "spotify:album:7dxKtc08dYeRVHt3p9CZJn"
      },
      {
        "album_type": "album",
        "artists": [
          {
            "external_urls": {
              "spotify": "https://open.spotify.com/artist/4Z8W4fKeB5YxbusRsdQVPb"
            },
            "href": "https://api.spotify.com/v1/artists/4Z8W4fKeB5YxbusRsdQVPb",
            "id": "4Z8W4fKeB5YxbusRsdQVPb",
            "name": "Radiohead",
            "type": "artist",
            "uri": "spotify:artist:4Z8W4fKeB5YxbusRsdQVPb"
          }
        ],
        "available_markets": [
          "AD",
          "AR",
          "AT",
          "AU",
          "BE",
          "BG",
          "BO",
          "BR",
          "CA",
          "CH",
          "CL",
          "CO",
          "CR",
          "CY",
          "CZ",
          "DE",
          "DK",
          "DO",
          "EC",
          "EE",
          "ES",
          "FI",
          "FR",
          "GB",
          "GR",
          "GT",
          "HK",
          "HN",
          "HU",
          "ID",
          "IE",
          "IL",
          "IS",
          "IT",
          "JP",
          "LI",
          "LT",
          "LU",
          "LV",
          "MC",
          "MT",
          "MX",
          "MY",
          "NI",
          "NL",
          "NO",
          "NZ",
          "PA",
          "PE",
          "PH",
          "PL",
          "PT",
          "PY",
          "RO",
          "SE",
          "SG",
          "SK",
          "SV",
          "TH",
          "TR",
          "TW",
          "US",
          "UY",
          "VN",
          "ZA"
        ],
        "external_urls": {
          "spotify": "https://open.spotify.com/album/6400dnyeDyD2mIFHfkwHXN"
        },
        "href": "https://api.spotify.com/v1/albums/6400dnyeDyD2mIFHfkwHXN",
        "id": "6400dnyeDyD2mIFHfkwHXN",
        "images": [
          {
            "height": 640,
            "url": "https://i.scdn.co/image/e17011b2aa33289dfa6c0828a0e40d6b56ad8820",
            "width": 640
          },
          {
            "height": 300,
            "url": "https://i.scdn.co/image/fe11a648ea61a3c2422c21b3ff8a870a6efbc608",
            "width": 300
          },
          {
            "height": 64,
            "url": "https://i.scdn.co/image/4b04fa350781271b1af24d804c1badec1f8e63c7",
            "width": 64
          }
        ],
        "name": "Pablo Honey",
        "release_date": "1993-02-22",
        "release_date_precision": "day",
        "type": "album",
        "uri": "spotify:album:6400dnyeDyD2mIFHfkwHXN"
      },
      {
        "album_type": "album",
        "artists": [
          {
            "external_urls": {
              "spotify": "https://open.spotify.com/artist/4Z8W4fKeB5YxbusRsdQVPb"
            },
            "href": "https://api.spotify.com/v1/artists/4Z8W4fKeB5YxbusRsdQVPb",
            "id": "4Z8W4fKeB5YxbusRsdQVPb",
            "name": "Radiohead",
            "type": "artist",
            "uri": "spotify:artist:4Z8W4fKeB5YxbusRsdQVPb"
          }
        ],
        "available_markets": [
          "AD",
          "AR",
          "AT",
          "AU",
          "BE",
          "BG",
          "BO",
          "BR",
          "CA",
          "CH",
          "CL",
          "CO",
          "CR",
          "CY",
          "CZ",
          "DE",
          "DK",
          "DO",
          "EC",
          "EE",
          "ES",
          "FI",
          "FR",
          "GB",
          "GR",
          "GT",
          "HK",
          "HN",
          "HU",
          "ID",
          "IE",
          "IL",
          "IS",
          "IT",
          "JP",
          "LI",
          "LT",
          "LU",
          "LV",
          "MC",
          "MT",
          "MX",
          "MY",
          "NI",
          "NL",
          "NO",
          "NZ",
          "PA",
          "PE",
          "PH",
          "PL",
          "PT",
          "PY",
          "RO",
          "SE",
          "SG",
          "SK",
          "SV",
          "TH",
          "TR",
          "TW",
          "US",
          "UY",
          "VN",
          "ZA"
        ],
        "external_urls": {
          "spotify": "https://open.spotify.com/album/7eyQXxuf2nGj9d2367Gi5f"
        },
        "href": "https://api.spotify.com/v1/albums/7eyQXxuf2nGj9d2367Gi5f",
        "id": "7eyQXxuf2nGj9d2367Gi5f",
        "images": [
          {
            "height": 640,
            "url": "https://i.scdn.co/image/00d97c99f9fb5872e9a44f06ae7e20fd011de125",
            "width": 640
          },
          {
            "height": 300,
            "url": "https://i.scdn.co/image/34c390dd70fca5ba873ec7bc27c0f15888e77f12",
            "width": 300
          },
          {
            "height": 64,
            "url": "https://i.scdn.co/image/c09778786823ad81376668f9187cb52d765ad77c",
            "width": 64
          }
        ],
        "name": "In Rainbows",
        "release_date": "2007-12-28",
        "release_date_precision": "day",
        "type": "album",
        "uri": "spotify:album:7eyQXxuf2nGj9d2367Gi5f"
      },
      {
        "album_type": "album",
        "artists": [
          {
            "external_urls": {
              "spotify": "https://open.spotify.com/artist/4Z8W4fKeB5YxbusRsdQVPb"
            },
            "href": "https://api.spotify.com/v1/artists/4Z8W4fKeB5YxbusRsdQVPb",
            "id": "4Z8W4fKeB5YxbusRsdQVPb",
            "name": "Radiohead",
            "type": "artist",
            "uri": "spotify:artist:4Z8W4fKeB5YxbusRsdQVPb"
          }
        ],
        "available_markets": [
          "AD",
          "AR",
          "AT",
          "AU",
          "BE",
          "BG",
          "BO",
          "BR",
          "CA",
          "CH",
          "CL",
          "CO",
          "CR",
          "CY",
          "CZ",
          "DE",
          "DK",
          "DO",
          "EC",
          "EE",
          "ES",
          "FI",
          "FR",
          "GB",
          "GR",
          "GT",
          "HK",
          "HN",
          "HU",
          "ID",
          "IE",
          "IL",
          "IS",
          "IT",
          "JP",
          "LI",
          "LT",
          "LU",
          "LV",
          "MC",
          "MT",
          "MX",
          "MY",
          "NI",
          "NL",
          "NO",
          "NZ",
          "PA",
          "PE",
          "PH",
          "PL",
          "PT",
          "PY",
          "RO",
          "SE",
          "SG",
          "SK",
          "SV",
          "TH",
          "TR",
          "TW",
          "US",
          "UY",
          "VN",
          "ZA"
        ],
        "external_urls": {
          "spotify": "https://open.spotify.com/album/500FEaUzn8lN9zWFyZG5C2"
        },
        "href": "https://api.spotify.com/v1/albums/500FEaUzn8lN9zWFyZG5C2",
        "id": "500FEaUzn8lN9zWFyZG5C2",
        "images": [
          {
            "height": 640,
            "url": "https://i.scdn.co/image/3a75fdf63322a8fdc86951eb836542093872530b",
            "width": 640
          },
          {
            "height": 300,
            "url": "https://i.scdn.co/image/391c85a80061f2e4cdc35c53d2a9ef86aff2502b",
            "width": 300
          },
          {
            "height": 64,
            "url": "https://i.scdn.co/image/668e4301cac2485e8a6573686c1b54c476d29f49",
            "width": 64
          }
        ],
        "name": "The Bends",
        "release_date": "1995-03-28",
        "release_date_precision": "day",
        "type": "album",
        "uri": "spotify:album:500FEaUzn8lN9zWFyZG5C2"
      },
      {
        "album_type": "album",
        "artists": [
          {
            "external_urls": {
              "spotify": "https://open.spotify.com/artist/4Z8W4fKeB5YxbusRsdQVPb"
            },
            "href": "https://api.spotify.com/v1/artists/4Z8W4fKeB5YxbusRsdQVPb",
            "id": "4Z8W4fKeB5YxbusRsdQVPb",
            "name": "Radiohead",
            "type": "artist",
            "uri": "spotify:artist:4Z8W4fKeB5YxbusRsdQVPb"
          }
        ],
        "available_markets": [
          "AD",
          "AR",
          "AT",
          "AU",
          "BE",
          "BG",
          "BO",
          "BR",
          "CA",
          "CH",
          "CL",
          "CO",
          "CR",
          "CY",
          "CZ",
          "DE",
          "DK",
          "DO",
          "EC",
          "EE",
          "ES",
          "FI",
          "FR",
          "GB",
          "GR",
          "GT",
          "HK",
          "HN",
          "HU",
          "ID",
          "IE",
          "IL",
          "IS",
          "IT",
          "JP",
          "LI",
          "LT",
          "LU",
          "LV",
          "MC",
          "MT",
          "MX",
          "MY",
          "NI",
          "NL",
          "NO",
          "NZ",
          "PA",
          "PE",
          "PH",
          "PL",
          "PT",
          "PY",
          "RO",
          "SE",
          "SG",
          "SK",
          "SV",
          "TH",
          "TR",
          "TW",
          "US",
          "UY",
          "VN",
          "ZA"
        ],
        "external_urls": {
          "spotify": "https://open.spotify.com/album/6vuykQgDLUCiZ7YggIpLM9"
        },
        "href": "https://api.spotify.com/v1/albums/6vuykQgDLUCiZ7YggIpLM9",
        "id": "6vuykQgDLUCiZ7YggIpLM9",
        "images": [
          {
            "height": 640,
            "url": "https://i.scdn.co/image/0d1460c036897175f4631e8480ea4a2217bf5447",
            "width": 640
          },
          {
            "height": 300,
            "url": "https://i.scdn.co/image/f24736fe22360da5fcb08fbca21d536e49eeca4a",
            "width": 300
          },
          {
            "height": 64,
            "url": "https://i.scdn.co/image/39f426b77d87a31e483d02d8049bf2c139f36ade",
            "width": 64
          }
        ],
        "name": "A Moon Shaped Pool",
        "release_date": "2016-05-08",
        "release_date_precision": "day",
        "type": "album",
        "uri": "spotify:album:6vuykQgDLUCiZ7YggIpLM9"
      },
      {
        "album_type": "album",
        "artists": [
          {
            "external_urls": {
              "spotify": "https://open.spotify.com/artist/4Z8W4fKeB5YxbusRsdQVPb"
            },
            "href": "https://api.spotify.com/v1/artists/4Z8W4fKeB5YxbusRsdQVPb",
            "id": "4Z8W4fKeB5YxbusRsdQVPb",
            "name": "Radiohead",
            "type": "artist",
            "uri": "spotify:artist:4Z8W4fKeB5YxbusRsdQVPb"
          }
        ],
        "available_markets": [
          "AD",
          "AR",
          "AT",
          "AU",
          "BE",
          "BG",
          "BO",
          "BR",
          "CA",
          "CH",
          "CL",
          "CO",
          "CR",
          "CY",
          "CZ",
          "DE",
          "DK",
          "DO",
          "EC",
          "EE",
          "ES",
          "FI",
          "FR",
          "GB",
          "GR",
          "GT",
          "HK",
          "HN",
          "HU",
          "ID",
          "IE",
          "IL",
          "IS",
          "IT",
          "JP",
          "LI",
          "LT",
          "LU",
          "LV",
          "MC",
          "MT",
          "MX",
          "MY",
          "NI",
          "NL",
          "NO",
          "NZ",
          "PA",
          "PE",
          "PH",
          "PL",
          "PT",
          "PY",
          "RO",
          "SE",
          "SG",
          "SK",
          "SV",
          "TH",
          "TR",
          "TW",
          "US",
          "UY",
          "VN",
          "ZA"
        ],
        "external_urls": {
          "spotify": "https://open.spotify.com/album/19RUXBFyM4PpmrLRdtqWbp"
        },
        "href": "https://api.spotify.com/v1/albums/19RUXBFyM4PpmrLRdtqWbp",
        "id": "19RUXBFyM4PpmrLRdtqWbp",
        "images": [
          {
            "height": 640,
            "url": "https://i.scdn.co/image/0a6b1c237ab9f7d7da0a04e3e5dba0f022daa20c",
            "width": 640
          },
          {
            "height": 300,
            "url": "https://i.scdn.co/image/c652dc46f7eb187075e19c0cc921421c3312e641",
            "width": 300
          },
          {
            "height": 64,
            "url": "https://i.scdn.co/image/d6ad92fcca2e4c7315bc240197e70ebaa7490cb0",
            "width": 64
          }
        ],
        "name": "Kid A",
        "release_date": "2000-10-01",
        "release_date_precision": "day",
        "type": "album",
        "uri": "spotify:album:19RUXBFyM4PpmrLRdtqWbp"
      },
      {
        "album_type": "album",
        "artists": [
          {
            "external_urls": {
              "spotify": "https://open.spotify.com/artist/4Z8W4fKeB5YxbusRsdQVPb"
            },
            "href": "https://api.spotify.com/v1/artists/4Z8W4fKeB5YxbusRsdQVPb",
            "id": "4Z8W4fKeB5YxbusRsdQVPb",
            "name": "Radiohead",
            "type": "artist",
            "uri": "spotify:artist:4Z8W4fKeB5YxbusRsdQVPb"
          }
        ],
        "available_markets": [
          "AD",
          "AR",
          "AT",
          "AU",
          "BE",
          "BG",
          "BO",
          "BR",
          "CA",
          "CH",
          "CL",
          "CO",
          "CR",
          "CY",
          "CZ",
          "DE",
          "DK",
          "DO",
          "EC",
          "EE",
          "ES",
          "FI",
          "FR",
          "GB",
          "GR",
          "GT",
          "HK",
          "HN",
          "HU",
          "ID",
          "IE",
          "IL",
          "IS",
          "IT",
          "JP",
          "LI",
          "LT",
          "LU",
          "LV",
          "MC",
          "MT",
          "MX",
          "MY",
          "NI",
          "NL",
          "NO",
          "NZ",
          "PA",
          "PE",
          "PH",
          "PL",
          "PT",
          "PY",
          "RO",
          "SE",
          "SG",
          "SK",
          "SV",
          "TH",
          "TR",
          "TW",
          "US",
          "UY",
          "VN",
          "ZA"
        ],
        "external_urls": {
          "spotify": "https://open.spotify.com/album/4ENxWWkPImVwAle9cpJ12I"
        },
        "href": "https://api.spotify.com/v1/albums/4ENxWWkPImVwAle9cpJ12I",
        "id": "4ENxWWkPImVwAle9cpJ12I",
        "images": [
          {
            "height": 640,
            "url": "https://i.scdn.co/image/9f858d307aa0bedbc2be9d4276ed39329d11ad92",
            "width": 640
          },
          {
            "height": 300,
            "url": "https://i.scdn.co/image/819b35407ee4fe3da687cbacd8017b4448f0775b",
            "width": 300
          },
          {
            "height": 64,
            "url": "https://i.scdn.co/image/9cc49b1c37b736ebcb7323f604fe81f3d0b64aa8",
            "width": 64
          }
        ],
        "name": "OK Computer OKNOTOK 1997 2017",
        "release_date": "2017-06-23",
        "release_date_precision": "day",
        "type": "album",
        "uri": "spotify:album:4ENxWWkPImVwAle9cpJ12I"
      },
      {
        "album_type": "album",
        "artists": [
          {
            "external_urls": {
              "spotify": "https://open.spotify.com/artist/4Z8W4fKeB5YxbusRsdQVPb"
            },
            "href": "https://api.spotify.com/v1/artists/4Z8W4fKeB5YxbusRsdQVPb",
            "id": "4Z8W4fKeB5YxbusRsdQVPb",
            "name": "Radiohead",
            "type": "artist",
            "uri": "spotify:artist:4Z8W4fKeB5YxbusRsdQVPb"
          }
        ],
        "available_markets": [
          "AD",
          "AR",
          "AT",
          "AU",
          "BE",
          "BG",
          "BO",
          "BR",
          "CA",
          "CH",
          "CL",
          "CO",
          "CR",
          "CY",
          "CZ",
          "DE",
          "DK",
          "DO",
          "EC",
          "EE",
          "ES",
          "FI",
          "FR",
          "GB",
          "GR",
          "GT",
          "HK",
          "HN",
          "HU",
          "ID",
          "IE",
          "IL",
          "IS",
          "IT",
          "JP",
          "LI",
          "LT",
          "LU",
          "LV",
          "MC",
          "MT",
          "MX",
          "MY",
          "NI",
          "NL",
          "NO",
          "NZ",
          "PA",
          "PE",
          "PH",
          "PL",
          "PT",
          "PY",
          "RO",
          "SE",
          "SG",
          "SK",
          "SV",
          "TH",
          "TR",
          "TW",
          "US",
          "UY",
          "VN",
          "ZA"
        ],
        "external_urls": {
          "spotify": "https://open.spotify.com/album/1oW3v5Har9mvXnGk0x4fHm"
        },
        "href": "https://api.spotify.com/v1/albums/1oW3v5Har9mvXnGk0x4fHm",
        "id": "1oW3v5Har9mvXnGk0x4fHm",
        "images": [
          {
            "height": 640,
            "url": "https://i.scdn.co/image/5ded47fd3d05325dd0faaf4619481e1f25a21ec7",
            "width": 640
          },
          {
            "height": 300,
            "url": "https://i.scdn.co/image/4bbc829fa1284c4cf85fdb62a599ae9e6e7d1c32",
            "width": 300
          },
          {
            "height": 64,
            "url": "https://i.scdn.co/image/d5fdc708551024ff72aa3ea57161473d7a7bebd5",
            "width": 64
          }
        ],
        "name": "Hail To the Thief",
        "release_date": "2003",
        "release_date_precision": "year",
        "type": "album",
        "uri": "spotify:album:1oW3v5Har9mvXnGk0x4fHm"
      },
      {
        "album_type": "album",
        "artists": [
          {
            "external_urls": {
              "spotify": "https://open.spotify.com/artist/4Z8W4fKeB5YxbusRsdQVPb"
            },
            "href": "https://api.spotify.com/v1/artists/4Z8W4fKeB5YxbusRsdQVPb",
            "id": "4Z8W4fKeB5YxbusRsdQVPb",
            "name": "Radiohead",
            "type": "artist",
            "uri": "spotify:artist:4Z8W4fKeB5YxbusRsdQVPb"
          }
        ],
        "available_markets": [
          "AD",
          "AR",
          "AT",
          "AU",
          "BE",
          "BG",
          "BO",
          "BR",
          "CA",
          "CH",
          "CL",
          "CO",
          "CR",
          "CY",
          "CZ",
          "DE",
          "DK",
          "DO",
          "EC",
          "EE",
          "ES",
          "FI",
          "FR",
          "GB",
          "GR",
          "GT",
          "HK",
          "HN",
          "HU",
          "ID",
          "IE",
          "IL",
          "IS",
          "IT",
          "JP",
          "LI",
          "LT",
          "LU",
          "LV",
          "MC",
          "MT",
          "MX",
          "MY",
          "NI",
          "NL",
          "NO",
          "NZ",
          "PA",
          "PE",
          "PH",
          "PL",
          "PT",
          "PY",
          "RO",
          "SE",
          "SG",
          "SK",
          "SV",
          "TH",
          "TR",
          "TW",
          "US",
          "UY",
          "VN",
          "ZA"
        ],
        "external_urls": {
          "spotify": "https://open.spotify.com/album/6V9YnBmFjWmXCBaUVRCVXP"
        },
        "href": "https://api.spotify.com/v1/albums/6V9YnBmFjWmXCBaUVRCVXP",
        "id": "6V9YnBmFjWmXCBaUVRCVXP",
        "images": [
          {
            "height": 640,
            "url": "https://i.scdn.co/image/7d2a9481f3136f8f9dda19bffa04c215257714c7",
            "width": 640
          },
          {
            "height": 300,
            "url": "https://i.scdn.co/image/b468b3f09ec4770493a8abf1ee17629be2276346",
            "width": 300
          },
          {
            "height": 64,
            "url": "https://i.scdn.co/image/15dac5d7f55f6b52fc299b1f175831be4e0f3008",
            "width": 64
          }
        ],
        "name": "Amnesiac",
        "release_date": "2001-03-12",
        "release_date_precision": "day",
        "type": "album",
        "uri": "spotify:album:6V9YnBmFjWmXCBaUVRCVXP"
      },
      {
        "album_type": "album",
        "artists": [
          {
            "external_urls": {
              "spotify": "https://open.spotify.com/artist/4Z8W4fKeB5YxbusRsdQVPb"
            },
            "href": "https://api.spotify.com/v1/artists/4Z8W4fKeB5YxbusRsdQVPb",
            "id": "4Z8W4fKeB5YxbusRsdQVPb",
            "name": "Radiohead",
            "type": "artist",
            "uri": "spotify:artist:4Z8W4fKeB5YxbusRsdQVPb"
          }
        ],
        "available_markets": [
          "AD",
          "AR",
          "AT",
          "AU",
          "BE",
          "BG",
          "BO",
          "BR",
          "CA",
          "CH",
          "CL",
          "CO",
          "CR",
          "CY",
          "CZ",
          "DE",
          "DK",
          "DO",
          "EC",
          "EE",
          "ES",
          "FI",
          "FR",
          "GB",
          "GR",
          "GT",
          "HK",
          "HN",
          "HU",
          "ID",
          "IE",
          "IL",
          "IS",
          "IT",
          "JP",
          "LI",
          "LT",
          "LU",
          "LV",
          "MC",
          "MT",
          "MX",
          "MY",
          "NI",
          "NL",
          "NO",
          "NZ",
          "PA",
          "PE",
          "PH",
          "PL",
          "PT",
          "PY",
          "RO",
          "SE",
          "SG",
          "SK",
          "SV",
          "TH",
          "TR",
          "TW",
          "US",
          "UY",
          "VN",
          "ZA"
        ],
        "external_urls": {
          "spotify": "https://open.spotify.com/album/1DBkJIEoeHrTX4WCBQGcCi"
        },
        "href": "https://api.spotify.com/v1/albums/1DBkJIEoeHrTX4WCBQGcCi",
        "id": "1DBkJIEoeHrTX4WCBQGcCi",
        "images": [
          {
            "height": 640,
            "url": "https://i.scdn.co/image/4a93b23fa39b39a4050a9510f2b8103772a1691c",
            "width": 640
          },
          {
            "height": 300,
            "url": "https://i.scdn.co/image/9f69ce2bb80c60914cd4caf761afa8b1657f4783",
            "width": 300
          },
          {
            "height": 64,
            "url": "https://i.scdn.co/image/a2d0934d5c4e54021d1271a91698febaf2bab310",
            "width": 64
          }
        ],
        "name": "The King Of Limbs",
        "release_date": "2011-02-18",
        "release_date_precision": "day",
        "type": "album",
        "uri": "spotify:album:1DBkJIEoeHrTX4WCBQGcCi"
      },
      {
        "album_type": "album",
        "artists": [
          {
            "external_urls": {
              "spotify": "https://open.spotify.com/artist/4Z8W4fKeB5YxbusRsdQVPb"
            },
            "href": "https://api.spotify.com/v1/artists/4Z8W4fKeB5YxbusRsdQVPb",
            "id": "4Z8W4fKeB5YxbusRsdQVPb",
            "name": "Radiohead",
            "type": "artist",
            "uri": "spotify:artist:4Z8W4fKeB5YxbusRsdQVPb"
          }
        ],
        "available_markets": [
          "AD",
          "AR",
          "AT",
          "AU",
          "BE",
          "BG",
          "BO",
          "BR",
          "CA",
          "CH",
          "CL",
          "CO",
          "CR",
          "CY",
          "CZ",
          "DE",
          "DK",
          "DO",
          "EC",
          "EE",
          "ES",
          "FI",
          "FR",
          "GB",
          "GR",
          "GT",
          "HK",
          "HN",
          "HU",
          "ID",
          "IE",
          "IL",
          "IS",
          "IT",
          "JP",
          "LI",
          "LT",
          "LU",
          "LV",
          "MC",
          "MT",
          "MX",
          "MY",
          "NI",
          "NL",
          "NO",
          "NZ",
          "PA",
          "PE",
          "PH",
          "PL",
          "PT",
          "PY",
          "RO",
          "SE",
          "SG",
          "SK",
          "SV",
          "TH",
          "TR",
          "TW",
          "US",
          "UY",
          "VN",
          "ZA"
        ],
        "external_urls": {
          "spotify": "https://open.spotify.com/album/36lJLPoPPOKNFddTAcirnc"
        },
        "href": "https://api.spotify.com/v1/albums/36lJLPoPPOKNFddTAcirnc",
        "id": "36lJLPoPPOKNFddTAcirnc",
        "images": [
          {
            "height": 640,
            "url": "https://i.scdn.co/image/02c6980b9f9e2a85342eb460adc5bd3df6505165",
            "width": 640
          },
          {
            "height": 300,
            "url": "https://i.scdn.co/image/342d56d055ced7a9af1fc23b9dbca93ccc3088cb",
            "width": 300
          },
          {
            "height": 64,
            "url": "https://i.scdn.co/image/8f2bffde33e37b3e07eec080d0c7e5bb9f0da7d2",
            "width": 64
          }
        ],
        "name": "In Rainbows Disk 2",
        "release_date": "2007",
        "release_date_precision": "year",
        "type": "album",
        "uri": "spotify:album:36lJLPoPPOKNFddTAcirnc"
      },
      {
        "album_type": "single",
        "artists": [
          {
            "external_urls": {
              "spotify": "https://open.spotify.com/artist/4Z8W4fKeB5YxbusRsdQVPb"
            },
            "href": "https://api.spotify.com/v1/artists/4Z8W4fKeB5YxbusRsdQVPb",
            "id": "4Z8W4fKeB5YxbusRsdQVPb",
            "name": "Radiohead",
            "type": "artist",
            "uri": "spotify:artist:4Z8W4fKeB5YxbusRsdQVPb"
          }
        ],
        "available_markets": [
          "AD",
          "AR",
          "AT",
          "AU",
          "BE",
          "BG",
          "BO",
          "BR",
          "CA",
          "CH",
          "CL",
          "CO",
          "CR",
          "CY",
          "CZ",
          "DE",
          "DK",
          "DO",
          "EC",
          "EE",
          "ES",
          "FI",
          "FR",
          "GB",
          "GR",
          "GT",
          "HK",
          "HN",
          "HU",
          "ID",
          "IE",
          "IL",
          "IS",
          "IT",
          "JP",
          "LI",
          "LT",
          "LU",
          "LV",
          "MC",
          "MT",
          "MX",
          "MY",
          "NI",
          "NL",
          "NO",
          "NZ",
          "PA",
          "PE",
          "PH",
          "PL",
          "PT",
          "PY",
          "RO",
          "SE",
          "SG",
          "SK",
          "SV",
          "TH",
          "TR",
          "TW",
          "US",
          "UY",
          "VN",
          "ZA"
        ],
        "external_urls": {
          "spotify": "https://open.spotify.com/album/4KzKj6JMBbIQ4QhbF3uQNR"
        },
        "href": "https://api.spotify.com/v1/albums/4KzKj6JMBbIQ4QhbF3uQNR",
        "id": "4KzKj6JMBbIQ4QhbF3uQNR",
        "images": [
          {
            "height": 640,
            "url": "https://i.scdn.co/image/2530d693ac3ff7b1dab4fefdc960c830a172901d",
            "width": 640
          },
          {
            "height": 300,
            "url": "https://i.scdn.co/image/0aafc6e04802d6aa6e62e1dd36b09df9d48d3d9e",
            "width": 300
          },
          {
            "height": 64,
            "url": "https://i.scdn.co/image/31f06bb03d4109c17223dc4a696ac23d2b48fc9a",
            "width": 64
          }
        ],
        "name": "Street Spirit (Fade Out)",
        "release_date": "1996-01-22",
        "release_date_precision": "day",
        "type": "album",
        "uri": "spotify:album:4KzKj6JMBbIQ4QhbF3uQNR"
      },
      {
        "album_type": "album",
        "artists": [
          {
            "external_urls": {
              "spotify": "https://open.spotify.com/artist/4Z8W4fKeB5YxbusRsdQVPb"
            },
            "href": "https://api.spotify.com/v1/artists/4Z8W4fKeB5YxbusRsdQVPb",
            "id": "4Z8W4fKeB5YxbusRsdQVPb",
            "name": "Radiohead",
            "type": "artist",
            "uri": "spotify:artist:4Z8W4fKeB5YxbusRsdQVPb"
          }
        ],
        "available_markets": [
          "AD",
          "AR",
          "AT",
          "AU",
          "BE",
          "BG",
          "BO",
          "BR",
          "CA",
          "CH",
          "CL",
          "CO",
          "CR",
          "CY",
          "CZ",
          "DE",
          "DK",
          "DO",
          "EC",
          "EE",
          "ES",
          "FI",
          "FR",
          "GB",
          "GR",
          "GT",
          "HK",
          "HN",
          "HU",
          "ID",
          "IE",
          "IL",
          "IS",
          "IT",
          "JP",
          "LI",
          "LT",
          "LU",
          "LV",
          "MC",
          "MT",
          "MX",
          "MY",
          "NI",
          "NL",
          "NO",
          "NZ",
          "PA",
          "PE",
          "PH",
          "PL",
          "PT",
          "PY",
          "RO",
          "SE",
          "SG",
          "SK",
          "SV",
          "TH",
          "TR",
          "TW",
          "US",
          "UY",
          "VN",
          "ZA"
        ],
        "external_urls": {
          "spotify": "https://open.spotify.com/album/47xaqCsJcYFWqD1gwujl1T"
        },
        "href": "https://api.spotify.com/v1/albums/47xaqCsJcYFWqD1gwujl1T",
        "id": "47xaqCsJcYFWqD1gwujl1T",
        "images": [
          {
            "height": 640,
            "url": "https://i.scdn.co/image/b22727002f64b3bd6dabe68a034f13ec413c3bfc",
            "width": 640
          },
          {
            "height": 300,
            "url": "https://i.scdn.co/image/d6f8b7931cc7a857ff8ddd3dd07613085154ac1a",
            "width": 300
          },
          {
            "height": 64,
            "url": "https://i.scdn.co/image/3f5fe77f9787f8cdbd221a2b6f8803a7bde46f1a",
            "width": 64
          }
        ],
        "name": "TKOL RMX 1234567",
        "release_date": "2011-10-10",
        "release_date_precision": "day",
        "type": "album",
        "uri": "spotify:album:47xaqCsJcYFWqD1gwujl1T"
      },
      {
        "album_type": "single",
        "artists": [
          {
            "external_urls": {
              "spotify": "https://open.spotify.com/artist/4Z8W4fKeB5YxbusRsdQVPb"
            },
            "href": "https://api.spotify.com/v1/artists/4Z8W4fKeB5YxbusRsdQVPb",
            "id": "4Z8W4fKeB5YxbusRsdQVPb",
            "name": "Radiohead",
            "type": "artist",
            "uri": "spotify:artist:4Z8W4fKeB5YxbusRsdQVPb"
          }
        ],
        "available_markets": [
          "AD",
          "AR",
          "AT",
          "AU",
          "BE",
          "BG",
          "BO",
          "BR",
          "CA",
          "CH",
          "CL",
          "CO",
          "CR",
          "CY",
          "CZ",
          "DE",
          "DK",
          "DO",
          "EC",
          "EE",
          "ES",
          "FI",
          "FR",
          "GB",
          "GR",
          "GT",
          "HK",
          "HN",
          "HU",
          "ID",
          "IE",
          "IL",
          "IS",
          "IT",
          "JP",
          "LI",
          "LT",
          "LU",
          "LV",
          "MC",
          "MT",
          "MX",
          "MY",
          "NI",
          "NL",
          "NO",
          "NZ",
          "PA",
          "PE",
          "PH",
          "PL",
          "PT",
          "PY",
          "RO",
          "SE",
          "SG",
          "SK",
          "SV",
          "TH",
          "TR",
          "TW",
          "US",
          "UY",
          "VN",
          "ZA"
        ],
        "external_urls": {
          "spotify": "https://open.spotify.com/album/6Eo5EkmdLvZrONzi046iC2"
        },
        "href": "https://api.spotify.com/v1/albums/6Eo5EkmdLvZrONzi046iC2",
        "id": "6Eo5EkmdLvZrONzi046iC2",
        "images": [
          {
            "height": 640,
            "url": "https://i.scdn.co/image/1b163be4ac290eac6740e0dabb4a140a72497e20",
            "width": 640
          },
          {
            "height": 300,
            "url": "https://i.scdn.co/image/e45b76a85740536c4de97bee81a56391b14d4ba8",
            "width": 300
          },
          {
            "height": 64,
            "url": "https://i.scdn.co/image/ac187e775b9f680e53150c8e528c539f9f42cb73",
            "width": 64
          }
        ],
        "name": "Com Lag: 2+2=5",
        "release_date": "2004-03-24",
        "release_date_precision": "day",
        "type": "album",
        "uri": "spotify:album:6Eo5EkmdLvZrONzi046iC2"
      },
      {
        "album_type": "album",
        "artists": [
          {
            "external_urls": {
              "spotify": "https://open.spotify.com/artist/4Z8W4fKeB5YxbusRsdQVPb"
            },
            "href": "https://api.spotify.com/v1/artists/4Z8W4fKeB5YxbusRsdQVPb",
            "id": "4Z8W4fKeB5YxbusRsdQVPb",
            "name": "Radiohead",
            "type": "artist",
            "uri": "spotify:artist:4Z8W4fKeB5YxbusRsdQVPb"
          }
        ],
        "available_markets": [
          "AD",
          "AR",
          "AT",
          "AU",
          "BE",
          "BG",
          "BO",
          "BR",
          "CA",
          "CH",
          "CL",
          "CO",
          "CR",
          "CY",
          "CZ",
          "DE",
          "DK",
          "DO",
          "EC",
          "EE",
          "ES",
          "FI",
          "FR",
          "GB",
          "GR",
          "GT",
          "HK",
          "HN",
          "HU",
          "ID",
          "IE",
          "IL",
          "IS",
          "IT",
          "JP",
          "LI",
          "LT",
          "LU",
          "LV",
          "MC",
          "MT",
          "MX",
          "MY",
          "NI",
          "NL",
          "NO",
          "NZ",
          "PA",
          "PE",
          "PH",
          "PL",
          "PT",
          "PY",
          "RO",
          "SE",
          "SG",
          "SK",
          "SV",
          "TH",
          "TR",
          "TW",
          "US",
          "UY",
          "VN",
          "ZA"
        ],
        "external_urls": {
          "spotify": "https://open.spotify.com/album/6svTt5o2lUgIrgYDKVmdnD"
        },
        "href": "https://api.spotify.com/v1/albums/6svTt5o2lUgIrgYDKVmdnD",
        "id": "6svTt5o2lUgIrgYDKVmdnD",
        "images": [
          {
            "height": 640,
            "url": "https://i.scdn.co/image/fb5a21ae19850c03216fea7e06b9d31e1ec1645c",
            "width": 640
          },
          {
            "height": 300,
            "url": "https://i.scdn.co/image/74e9e7660d8a09123efb6277508e324d61610c32",
            "width": 300
          },
          {
            "height": 64,
            "url": "https://i.scdn.co/image/9f30acbc7e3c5c19a5c94408a37ad0313b3e9f3c",
            "width": 64
          }
        ],
        "name": "I Might Be Wrong",
        "release_date": "2001",
        "release_date_precision": "year",
        "type": "album",
        "uri": "spotify:album:6svTt5o2lUgIrgYDKVmdnD"
      },
      {
        "album_type": "single",
        "artists": [
          {
            "external_urls": {
              "spotify": "https://open.spotify.com/artist/4Z8W4fKeB5YxbusRsdQVPb"
            },
            "href": "https://api.spotify.com/v1/artists/4Z8W4fKeB5YxbusRsdQVPb",
            "id": "4Z8W4fKeB5YxbusRsdQVPb",
            "name": "Radiohead",
            "type": "artist",
            "uri": "spotify:artist:4Z8W4fKeB5YxbusRsdQVPb"
          }
        ],
        "available_markets": [
          "AD",
          "AR",
          "AT",
          "AU",
          "BE",
          "BG",
          "BO",
          "BR",
          "CA",
          "CH",
          "CL",
          "CO",
          "CR",
          "CY",
          "CZ",
          "DE",
          "DK",
          "DO",
          "EC",
          "EE",
          "ES",
          "FI",
          "FR",
          "GB",
          "GR",
          "GT",
          "HK",
          "HN",
          "HU",
          "ID",
          "IE",
          "IL",
          "IS",
          "IT",
          "JP",
          "LI",
          "LT",
          "LU",
          "LV",
          "MC",
          "MT",
          "MX",
          "MY",
          "NI",
          "NL",
          "NO",
          "NZ",
          "PA",
          "PE",
          "PH",
          "PL",
          "PT",
          "PY",
          "RO",
          "SE",
          "SG",
          "SK",
          "SV",
          "TH",
          "TR",
          "TW",
          "US",
          "UY",
          "VN",
          "ZA"
        ],
        "external_urls": {
          "spotify": "https://open.spotify.com/album/6xEJ4AkNz1FFNmDT2rbEjM"
        },
        "href": "https://api.spotify.com/v1/albums/6xEJ4AkNz1FFNmDT2rbEjM",
        "id": "6xEJ4AkNz1FFNmDT2rbEjM",
        "images": [
          {
            "height": 640,
            "url": "https://i.scdn.co/image/9c6e8ecd1c6344afe8c60fba5e298eaf0262e816",
            "width": 640
          },
          {
            "height": 300,
            "url": "https://i.scdn.co/image/11b6bde0c6fa8b2526d9faa31c6795781eb328db",
            "width": 300
          },
          {
            "height": 64,
            "url": "https://i.scdn.co/image/6a0eaa789131102671c6d74bb38af317dd953e16",
            "width": 64
          }
        ],
        "name": "Spectre",
        "release_date": "2016-05-07",
        "release_date_precision": "day",
        "type": "album",
        "uri": "spotify:album:6xEJ4AkNz1FFNmDT2rbEjM"
      },
      {
        "album_type": "single",
        "artists": [
          {
            "external_urls": {
              "spotify": "https://open.spotify.com/artist/4Z8W4fKeB5YxbusRsdQVPb"
            },
            "href": "https://api.spotify.com/v1/artists/4Z8W4fKeB5YxbusRsdQVPb",
            "id": "4Z8W4fKeB5YxbusRsdQVPb",
            "name": "Radiohead",
            "type": "artist",
            "uri": "spotify:artist:4Z8W4fKeB5YxbusRsdQVPb"
          }
        ],
        "available_markets": [
          "AD",
          "AR",
          "AT",
          "AU",
          "BE",
          "BG",
          "BO",
          "BR",
          "CA",
          "CH",
          "CL",
          "CO",
          "CR",
          "CY",
          "CZ",
          "DE",
          "DK",
          "DO",
          "EC",
          "EE",
          "ES",
          "FI",
          "FR",
          "GB",
          "GR",
          "GT",
          "HK",
          "HN",
          "HU",
          "ID",
          "IE",
          "IL",
          "IS",
          "IT",
          "JP",
          "LI",
          "LT",
          "LU",
          "LV",
          "MC",
          "MT",
          "MX",
          "MY",
          "NI",
          "NL",
          "NO",
          "NZ",
          "PA",
          "PE",
          "PH",
          "PL",
          "PT",
          "PY",
          "RO",
          "SE",
          "SG",
          "SK",
          "SV",
          "TH",
          "TR",
          "TW",
          "US",
          "UY",
          "VN",
          "ZA"
        ],
        "external_urls": {
          "spotify": "https://open.spotify.com/album/2yepd22RxJzI9RiLFiUQOZ"
        },
        "href": "https://api.spotify.com/v1/albums/2yepd22RxJzI9RiLFiUQOZ",
        "id": "2yepd22RxJzI9RiLFiUQOZ",
        "images": [
          {
            "height": 640,
            "url": "https://i.scdn.co/image/1da049cfa90b3c19a82bfaf0c9702e84942ba93f",
            "width": 640
          },
          {
            "height": 300,
            "url": "https://i.scdn.co/image/0976b6e2d1a1e167c47401d209e29988fbce8011",
            "width": 300
          },
          {
            "height": 64,
            "url": "https://i.scdn.co/image/7d24a656f9c3ac26158669a7356cabe5371edd31",
            "width": 64
          }
        ],
        "name": "The Daily Mail / Staircase",
        "release_date": "2011-12-19",
        "release_date_precision": "day",
        "type": "album",
        "uri": "spotify:album:2yepd22RxJzI9RiLFiUQOZ"
      },
      {
        "album_type": "single",
        "artists": [
          {
            "external_urls": {
              "spotify": "https://open.spotify.com/artist/4Z8W4fKeB5YxbusRsdQVPb"
            },
            "href": "https://api.spotify.com/v1/artists/4Z8W4fKeB5YxbusRsdQVPb",
            "id": "4Z8W4fKeB5YxbusRsdQVPb",
            "name": "Radiohead",
            "type": "artist",
            "uri": "spotify:artist:4Z8W4fKeB5YxbusRsdQVPb"
          }
        ],
        "available_markets": [
          "AD",
          "AR",
          "AT",
          "AU",
          "BE",
          "BG",
          "BO",
          "BR",
          "CA",
          "CH",
          "CL",
          "CO",
          "CR",
          "CY",
          "CZ",
          "DE",
          "DK",
          "DO",
          "EC",
          "EE",
          "ES",
          "FI",
          "FR",
          "GB",
          "GR",
          "GT",
          "HK",
          "HN",
          "HU",
          "ID",
          "IE",
          "IL",
          "IS",
          "IT",
          "JP",
          "LI",
          "LT",
          "LU",
          "LV",
          "MC",
          "MT",
          "MX",
          "MY",
          "NI",
          "NL",
          "NO",
          "NZ",
          "PA",
          "PE",
          "PH",
          "PL",
          "PT",
          "PY",
          "RO",
          "SE",
          "SG",
          "SK",
          "SV",
          "TH",
          "TR",
          "TW",
          "US",
          "UY",
          "VN",
          "ZA"
        ],
        "external_urls": {
          "spotify": "https://open.spotify.com/album/6XddWLjwauCA6a17FM8pDb"
        },
        "href": "https://api.spotify.com/v1/albums/6XddWLjwauCA6a17FM8pDb",
        "id": "6XddWLjwauCA6a17FM8pDb",
        "images": [
          {
            "height": 640,
            "url": "https://i.scdn.co/image/eeecbaabb8ef2b120776924f0df2d93d59e3bfb0",
            "width": 640
          },
          {
            "height": 300,
            "url": "https://i.scdn.co/image/e00b79980350e53d3aa7cb726bbfcb75d55c83d9",
            "width": 300
          },
          {
            "height": 64,
            "url": "https://i.scdn.co/image/3a5659e5a7ebc3e5bd95a2861f00e07f266787da",
            "width": 64
          }
        ],
        "name": "My Iron Lung",
        "release_date": "1994-09-26",
        "release_date_precision": "day",
        "type": "album",
        "uri": "spotify:album:6XddWLjwauCA6a17FM8pDb"
      },
      {
        "album_type": "album",
        "artists": [
          {
            "external_urls": {
              "spotify": "https://open.spotify.com/artist/5bHjVR4F2Tfq4Ha6x7K6wU"
            },
            "href": "https://api.spotify.com/v1/artists/5bHjVR4F2Tfq4Ha6x7K6wU",
            "id": "5bHjVR4F2Tfq4Ha6x7K6wU",
            "name": "Rockabye Baby!",
            "type": "artist",
            "uri": "spotify:artist:5bHjVR4F2Tfq4Ha6x7K6wU"
          }
        ],
        "available_markets": [
          "AD",
          "AR",
          "AT",
          "AU",
          "BE",
          "BG",
          "BO",
          "BR",
          "CA",
          "CH",
          "CL",
          "CO",
          "CR",
          "CY",
          "CZ",
          "DE",
          "DK",
          "DO",
          "EC",
          "EE",
          "ES",
          "FI",
          "FR",
          "GB",
          "GR",
          "GT",
          "HK",
          "HN",
          "HU",
          "ID",
          "IE",
          "IL",
          "IS",
          "IT",
          "JP",
          "LI",
          "LT",
          "LU",
          "LV",
          "MC",
          "MT",
          "MX",
          "MY",
          "NI",
          "NL",
          "NO",
          "NZ",
          "PA",
          "PE",
          "PH",
          "PL",
          "PT",
          "PY",
          "RO",
          "SE",
          "SG",
          "SK",
          "SV",
          "TH",
          "TR",
          "TW",
          "US",
          "UY",
          "VN",
          "ZA"
        ],
        "external_urls": {
          "spotify": "https://open.spotify.com/album/2jCCFU789Xzw5W8i07UjRb"
        },
        "href": "https://api.spotify.com/v1/albums/2jCCFU789Xzw5W8i07UjRb",
        "id": "2jCCFU789Xzw5W8i07UjRb",
        "images": [
          {
            "height": 640,
            "url": "https://i.scdn.co/image/6ea955ec584a2524ba29f7ab4b3a2abb025f32f3",
            "width": 640
          },
          {
            "height": 300,
            "url": "https://i.scdn.co/image/e539f58415d4f1b4bf1ed325d660bcbb909c2434",
            "width": 300
          },
          {
            "height": 64,
            "url": "https://i.scdn.co/image/ddc84dcfac042081ddbbf93d71293aa72ef32857",
            "width": 64
          }
        ],
        "name": "Lullaby Renditions of Radiohead",
        "release_date": "2007-03-13",
        "release_date_precision": "day",
        "type": "album",
        "uri": "spotify:album:2jCCFU789Xzw5W8i07UjRb"
      },
      {
        "album_type": "single",
        "artists": [
          {
            "external_urls": {
              "spotify": "https://open.spotify.com/artist/4Z8W4fKeB5YxbusRsdQVPb"
            },
            "href": "https://api.spotify.com/v1/artists/4Z8W4fKeB5YxbusRsdQVPb",
            "id": "4Z8W4fKeB5YxbusRsdQVPb",
            "name": "Radiohead",
            "type": "artist",
            "uri": "spotify:artist:4Z8W4fKeB5YxbusRsdQVPb"
          }
        ],
        "available_markets": [
          "AD",
          "AR",
          "AT",
          "AU",
          "BE",
          "BG",
          "BO",
          "BR",
          "CA",
          "CH",
          "CL",
          "CO",
          "CR",
          "CY",
          "CZ",
          "DE",
          "DK",
          "DO",
          "EC",
          "EE",
          "ES",
          "FI",
          "FR",
          "GB",
          "GR",
          "GT",
          "HK",
          "HN",
          "HU",
          "ID",
          "IE",
          "IL",
          "IS",
          "IT",
          "JP",
          "LI",
          "LT",
          "LU",
          "LV",
          "MC",
          "MT",
          "MX",
          "MY",
          "NI",
          "NL",
          "NO",
          "NZ",
          "PA",
          "PE",
          "PH",
          "PL",
          "PT",
          "PY",
          "RO",
          "SE",
          "SG",
          "SK",
          "SV",
          "TH",
          "TR",
          "TW",
          "US",
          "UY",
          "VN",
          "ZA"
        ],
        "external_urls": {
          "spotify": "https://open.spotify.com/album/2DCzgO12HyMeGxoQlbtvQV"
        },
        "href": "https://api.spotify.com/v1/albums/2DCzgO12HyMeGxoQlbtvQV",
        "id": "2DCzgO12HyMeGxoQlbtvQV",
        "images": [
          {
            "height": 640,
            "url": "https://i.scdn.co/image/fc67258a36d4631239593313bdd55a16be3885f6",
            "width": 640
          },
          {
            "height": 300,
            "url": "https://i.scdn.co/image/0347525b6030078ef0b51197c68c0d49cbc8cfc6",
            "width": 300
          },
          {
            "height": 64,
            "url": "https://i.scdn.co/image/d5e4b190bfc314a97bbbb1ef687e3ee08add5faa",
            "width": 64
          }
        ],
        "name": "Burn the Witch",
        "release_date": "2016-05-03",
        "release_date_precision": "day",
        "type": "album",
        "uri": "spotify:album:2DCzgO12HyMeGxoQlbtvQV"
      }
    ],
    "limit": 20,
    "next": "https://api.spotify.com/v1/search?query=radiohead&type=album&market=US&offset=20&limit=20",
    "offset": 0,
    "previous": null,
    "total": 168
  }
}